beetmoverscript/__init__.py
beetmoverscript/constants.py
beetmoverscript/maven_utils.py
beetmoverscript/script.py
beetmoverscript/task.py
beetmoverscript/utils.py
beetmoverscript/zip.py
beetmoverscript/data/artifactMap_beetmover_task_schema.json
beetmoverscript/data/beetmover_task_schema.json
beetmoverscript/data/maven_beetmover_task_schema.json
beetmoverscript/data/release_beetmover_task_schema.json
beetmoverscript/templates/devedition_candidates.yml
beetmoverscript/templates/devedition_candidates_repacks.yml
beetmoverscript/templates/firefox_candidates.yml
beetmoverscript/templates/firefox_candidates_repacks.yml
beetmoverscript/templates/firefox_partner.yml
beetmoverscript/templates/firefox_partner_repacks.yml
beetmoverscript/templates/thunderbird_candidates.yml
beetmoverscript/templates/thunderbird_candidates_repacks.yml
beetmoverscript/templates/thunderbird_nightly.yml
beetmoverscript/templates/thunderbird_nightly_repacks.yml
beetmoverscript/test/__init__.py
beetmoverscript/test/fake_artifact.json
beetmoverscript/test/fake_beetmover_partner_manifest.yml
beetmoverscript/test/fake_config.json
beetmoverscript/test/test_maven_utils.py
beetmoverscript/test/test_script.py
beetmoverscript/test/test_task.py
beetmoverscript/test/test_utils.py
beetmoverscript/test/test_zip.py
beetmoverscript/test/templates/fake_nightly.yml
beetmoverscript/test/test_artifact_dir/public/dummy.checksums
beetmoverscript/test/test_artifact_dir/public/manifest.json
beetmoverscript/test/test_artifact_dir/public/target.checksums
beetmoverscript/test/test_work_dir/task.json
beetmoverscript/test/test_work_dir/task_artifact_map.json
beetmoverscript/test/test_work_dir/task_devedition.json
beetmoverscript/test/test_work_dir/task_fennec.json
beetmoverscript/test/test_work_dir/task_missing_installer.json
beetmoverscript/test/test_work_dir/task_missing_relprops.json
beetmoverscript/test/test_work_dir/task_partials.json
beetmoverscript-8.5.6.dist-info/LICENSE
beetmoverscript-8.5.6.dist-info/METADATA
beetmoverscript-8.5.6.dist-info/WHEEL
beetmoverscript-8.5.6.dist-info/entry_points.txt
beetmoverscript-8.5.6.dist-info/top_level.txt
beetmoverscript-8.5.6.dist-info/RECORD
