Metadata-Version: 2.1
Name: beetmoverscript
Version: 8.5.6
Summary: TaskCluster Beetmover Script
Home-page: https://github.com/mozilla-releng/beetmoverscript/
Author: Mozilla Release Engineering
Author-email: release+python@mozilla.com
License: MPL2
Platform: UNKNOWN
Classifier: Intended Audience :: Developers
Classifier: Natural Language :: English
Classifier: Programming Language :: Python :: 3.6
Classifier: Programming Language :: Python :: 3.7
Requires-Dist: Jinja2
Requires-Dist: boto3
Requires-Dist: mozilla-version
Requires-Dist: redo
Requires-Dist: scriptworker
